LICENSE
README.md
setup.cfg
setup.py
target_stitch/__init__.py
target_stitch.egg-info/PKG-INFO
target_stitch.egg-info/SOURCES.txt
target_stitch.egg-info/dependency_links.txt
target_stitch.egg-info/entry_points.txt
target_stitch.egg-info/requires.txt
target_stitch.egg-info/top_level.txt