Metadata-Version: 2.1
Name: target-stitch
Version: 4.0.0
Summary: Singer.io target for the Stitch API
Home-page: https://singer.io
Author: Stitch
Classifier: Programming Language :: Python :: 3 :: Only
Provides-Extra: dev
License-File: LICENSE
